pyutils/__init__.py
pyutils/datetime_utils/__init__.py
pyutils/datetime_utils/json_datetime_encoder.py
pyutils/json_utils/__init__.py
pyutils/json_utils/multiple_json_encoders.py
pyutils/pint_utils/__init__.py
pyutils/pint_utils/json_pint_encoder.py
pyutils/pint_utils/unit_manager.py
pyutils_AlexHenderson-1.1.1.dist-info/LICENSE
pyutils_AlexHenderson-1.1.1.dist-info/METADATA
pyutils_AlexHenderson-1.1.1.dist-info/WHEEL
pyutils_AlexHenderson-1.1.1.dist-info/top_level.txt
pyutils_AlexHenderson-1.1.1.dist-info/RECORD
