Metadata-Version: 2.1
Name: pyutils-AlexHenderson
Version: 1.1.1
Summary: Various python utilities
Home-page: https://github.com/AlexHenderson/pyutils
Author: Alex Henderson
Author-email: alex.henderson@manchester.ac.uk
License: UNKNOWN
Project-URL: Bug Tracker, https://github.com/AlexHenderson/pyutils/issues
Platform: UNKNOWN
Classifier: Programming Language :: Python :: 3
Classifier: Programming Language :: Python :: 3.7
Classifier: License :: OSI Approved :: MIT License
Classifier: Operating System :: OS Independent
Classifier: Development Status :: 5 - Production/Stable
Classifier: Intended Audience :: Developers
Requires-Python: >=3.7
License-File: LICENSE
Requires-Dist: pint
